Workbook

Sheet Inputs
B2: Demand | C2: Units | D2: Cost Lo | E2: Cost Hi | F2: Units | G2: Value Lo ($/y) | H2: Value Hi ($/y) | I2: Value AVG ($/y) | J2: Notes
A3: Water | B3: =B17 -> 4.5238934e+09 | C3: L/y | D3: 3.86 | E3: 3.86 | F3: $/kgal | G3: =(B3*D3)/(1000*3.78541) -> 4613034.9 | H3: =(B3*E3)/(1000*3.78541) -> 4613034.9 | I3: =AVERAGE(G3:H3) -> 4613034.9 | J3: Assuming 50% water reuse
A4: Glucose | B4: =(B3*100)/(1000*1000) -> 452389.34 | C4: t/y | D4: 450 | E4: 4885 | F4: $/t | G4: =B4*D4 -> 2.035752e+08 | H4: =B4*E4 -> 2.2099219e+09 | I4: =AVERAGE(G4:H4) -> 1.2067486e+09 | J4: 100 g / L
A5: Yeast Extract | B5: =0.05*B4 -> 22619.467 | C5: t/y | D5: 3000 | E5: =(169*1000*1000)/6000 -> 28166.667 | F5: $/t | G5: =B5*D5 -> 67858401 | H5: =B5*E5 -> 6.3711499e+08 | I5: =AVERAGE(G5:H5) -> 3.524867e+08 | J5: 0.05 g YE per g glucose
A6: Sodium Hydroxide | B6: =(B3*0.001*40)/(1000*1000) -> 180.95574 | C6: t/y | D6: 280 | E6: 495.6 | F6: $/t | G6: =B6*D6 -> 50667.606 | H6: =B6*E6 -> 89681.663 | I6: =AVERAGE(G6:H6) -> 70174.635 | J6: Increasing pH from 3 to 8
G7: =SUM(G3:G5) -> 2.7604664e+08 | H7: =SUM(H3:H5) -> 2.85165e+09 | I7: =SUM(I3:I5) -> 1.5638483e+09
A17: Water Calculation (L/y) | B17: =(B19*1000*1000)/(B18*1000) -> 4.5238934e+09
A18: Pulp Density (g rock/10 mL biolixiviant) | B18: 0.6
A19: Rocks (t/y) | B19: =A33 -> 2714336.1
A26: =(A27/3.14159265358979)^0.5 -> 126.15663 | B26: radius (m) for leaching pad
A27: 50000 | B27: heap area per membrane (m2)
A28: =A26/2 -> 63.078313 | B28: height (m) for 2:1 horizontal:vertical heap height
A29: 120 | B29: radius (m) for heap (decreased for buffer room)
A30: 60 | B30: height (m) for 2:1 horizontal:vertical heap height (decreased for buffer space)
A31: =(1/3)*(3.14159265358979)*(A29^2)*(A30) -> 904778.68 | B31: volume (m3) of cone-shaped heap
A32: 3 | B32: rock density, accounting for voids from powdering (g / cm3) | C32: http://deepseadrilling.org/37/Volume/dsdp37_13.pdf
A33: =(A31*A32) -> 2714336.1 | B33: mass (tonne/y) of leached rocks (1x heap mass)

Sheet Capital Costs
B1: Q (L/y) | C1: HRT (d) | D1: V (L) | E1: Size (ea) | F1: Units | G1: Units (in use) | H1: Tanks (Increased by 20% for contingency) | I1: 2014 Price (USD) | J1: # of Units | K1: 2014 Total (USD) | L1: 2025 USD | M1: Annualized Cost | N1: Parameters | O1: Source
A2: Growth & Biolixiviant Production Tanks | B2: =Inputs!B3 -> 4.5238934e+09 | C2: =(48+42)/24 -> 3.75 | D2: =B2*C2/$B$19 -> 56548668 | E2: 70000 | F2: gal | G2: =D2/(E2*3.78541) -> 213.40835 | H2: =1.2*G2 -> 256.09002 | I2: 84200 | J2: 257 | K2: =I2*J2 -> 21639400 | L2: =(B21/B20)*K2 -> 30725619 | M2: =L2/20 -> 1536281 | N2: Horiz, Round Ends, 70000 gal | O2: https://www.matche.com/equipcost/Tank.html
A3: Agitator | G3: =G2 -> 213.40835 | I3: 12200 | J3: =J2 -> 257 | K3: =I3*J3 -> 3135400 | L3: =(B21/B20)*K3 -> 4451930.6 | M3: =L3/20 -> 222596.53 | N3: Turbine, Top Entering, (14.14 kW), Carbon Steel, Atmospheric Internal Pressure | O3: https://www.matche.com/equipcost/Agitator.html
A4: Diffuser | G4: =20*G2 -> 4268.167 | J4: =20*J2 -> 5140 | L4: =129.99*J4 -> 668148.6 | M4: =L4/20 -> 33407.43 | N4: WBCB304-24 - SSI Aeration - Wide Band Coarse Bubble Diffuser in 304 Stainless Steel x 24’’ Length - Original | O4: https://www.amazon.com/WBCB304-24-Aeration-Diffuser-Stainless-Original/dp/B07KBCF677
A5: Air Pump | G5: =G2 -> 213.40835 | I5: =I14 -> 124700 | J5: =J2*B35 -> 257 | K5: =I5*J5 -> 32047900 | L5: =(B21/B20)*K5 -> 45504569 | M5: =L5/20 -> 2275228.4 | N5: Centrifugal, large, 70,000 cfm | O5: https://www.matche.com/equipcost/Blower.html
A6: Liquid Pump | G6: =2*G2 -> 426.8167 | I6: 11500 | J6: =2*J2 -> 514 | K6: =I6*J6 -> 5911000 | L6: =(B21/B20)*K6 -> 8392983.9 | M6: =L6/20 -> 419649.19 | N6: Horizontal, ANSI, 1-Stage Centrifugal Pump, 8 inch Discharge Pipe Diameter; Cast Iron & API-610, Packing Seal Type | O6: https://www.matche.com/equipcost/PumpCentr.html
A7: Clarifier | C7: =2/24 -> 0.083333333 | G7: 1 | I7: =I2 -> 84200 | J7: 2 | L7: =174000*J7 -> 348000 | M7: =L7/20 -> 17400 | N7: SuperPro | O7: https://www.matche.com/equipcost/Tank.html
A8: Liquid Pump | G8: =(B2)/(350*3.78541*60*24*B19) -> 7.904013 | H8: =1.2*G8 -> 9.4848157 | I8: =I6 -> 11500 | J8: 10 | K8: =28800*J8 -> 288000 | L8: =(B21/B20)*K8 -> 408929.01 | M8: =L8/20 -> 20446.45 | N8: Horizontal, ANSI, 1-Stage Centrifugal Pump, 8 inch Discharge Pipe Diameter; Cast Iron & API-610, Packing Seal Type | O8: https://www.matche.com/equipcost/PumpCentr.html
A9: Heap | B9: =B2 -> 4.5238934e+09 | J9: 1 | L9: =3*10.7639104*50000 -> 1614586.6 | M9: =L9/20 -> 80729.328 | N9: $3 per ft2, 50,000 m2 max unless customized per https://www.alibaba.com/product-detail/Heap-Leach-Geomembrane-Pond-Liner-Waterproof_1601125742047.html | O9: correspondence with industry
A10: Liquid Pump | G10: =G6 -> 426.8167 | H10: =H8 -> 9.4848157 | I10: =I6 -> 11500 | J10: 10 | K10: =28800*J10 -> 288000 | L10: =(B21/B20)*K10 -> 408929.01 | M10: =L10/20 -> 20446.45 | N10: Horizontal, ANSI, 1-Stage Centrifugal Pump, 8 inch Discharge Pipe Diameter; Cast Iron & API-610, Packing Seal Type | O10: https://www.matche.com/equipcost/PumpCentr.html
A11: Carbonate Formation Tanks | B11: =B2 -> 4.5238934e+09 | C11: 10 | D11: =B11*C11/$B$19 -> 1.5079645e+08 | E11: 70000 | F11: gal | G11: =D11/(E11*3.78541) -> 569.08894 | H11: =1.2*G11 -> 682.90673 | I11: =I2 -> 84200 | J11: 683 | K11: =84200*J11 -> 57508600 | L11: =(B21/B20)*K11 -> 81656023 | M11: =L11/20 -> 4082801.1 | N11: Horiz, Round Ends, 70000 gal | O11: https://www.matche.com/equipcost/Tank.html
A12: Agitator | G12: =G11 -> 569.08894 | I12: =I3 -> 12200 | J12: =J11 -> 683 | K12: =I12*J12 -> 8332600 | L12: =(B21/B20)*K12 -> 11831395 | M12: =L12/20 -> 591569.76 | N12: Turbine, Top Entering, (14.14 kW), Carbon Steel, Atmospheric Internal Pressure | O12: https://www.matche.com/equipcost/Agitator.html
A13: Diffuser | G13: =20*G11 -> 11381.779 | J13: =20*J11 -> 13660 | L13: =129.99*J13 -> 1775663.4 | M13: =L13/20 -> 88783.17 | N13: WBCB304-24 - SSI Aeration - Wide Band Coarse Bubble Diffuser in 304 Stainless Steel x 24’’ Length - Original | O13: https://www.amazon.com/WBCB304-24-Aeration-Diffuser-Stainless-Original/dp/B07KBCF677
A14: Air Pump | G14: =B36*G11 -> 3414.5336 | I14: 124700 | J14: 4098 | K14: =I14*J14 -> 511020600 | L14: =(B21/B20)*K14 -> 7.2559426e+08 | M14: =L14/20 -> 36279713 | N14: Centrifugal, large, 70,000 cfm | O14: https://www.matche.com/equipcost/Blower.html
A15: Liquid Pump | G15: =G11 -> 569.08894 | I15: 11500 | J15: =J11 -> 683 | K15: =I15*J15 -> 7854500 | L15: =(B21/B20)*K15 -> 11152545 | M15: =L15/20 -> 557627.23 | N15: Horizontal, ANSI, 1-Stage Centrifugal Pump, 8 inch Discharge Pipe Diameter; Cast Iron & API-610, Packing Seal Type | O15: https://www.matche.com/equipcost/PumpCentr.html
K16: PEC | L16: =SUM(L2:L15) -> 9.2453358e+08 | M16: =L16/20 -> 46226679
A18: Assumptions
A19: Working days/y | B19: 300
A20: CEPI 2014 | B20: 576.1
A21: CEPI 2025 | B21: 818
B25: Total | C25: 2025 USD Price
A26: Tanks | B26: =J2+J11 -> 940 | C26: =(B21/B20)*I2 -> 119554.94 | D26: =B26*C26 -> 1.1238164e+08
A27: Agitators | B27: =J3+J12 -> 940 | C27: =(B21/B20)*I3 -> 17322.687 | D27: =B27*C27 -> 16283326
A28: Diffusers | B28: =J4+J13 -> 18800
A29: Air Pumps (Total, Unrounded, Growth & Biolixiviant Production) | B29: =B35*H2 -> 256.09002
A30: Air Pumps (Total, Unrounded, Carbonate Formation) | B30: =B36*H11 -> 4097.4404
A31: Air Pumps (Total, Rounded, Growth & Biolixiviant Production) | B31: 257
A32: Air Pumps (Total, Rounded, Carbonate Formation) | B32: 4098
A33: Air Pumps (Total) | B33: =SUM(B31:B32) -> 4355 | C33: =(B21/B20)*I5 -> 177060.58 | D33: =B33*C33 -> 7.7109882e+08
A34: Liquid Pumps | B34: =J6+J8+J10+J15 -> 1217 | C34: =(B21/B20)*I6 -> 16328.762 | D34: =B34*C34 -> 19872104
A35: Air Pumps Per Growth & Biolixiviant Production Tank | B35: 1
A36: Air Pumps Per Carbonate Formation Tanks | B36: 6

Sheet Operating Costs
H1: Source
A2: Electricity | B2: kW | C2: Units (In Use Full Time) | D2: Hours/y | E2: kWh/y | F2: $/kWh | G2: $/y | H2: Sum of agitation, air pump, and liquid pump
A3: Electricity - agitation | B3: 14.14 | C3: =('Capital Costs'!G3+'Capital Costs'!G12) -> 782.49729 | D3: =24*'Capital Costs'!B19 -> 7200 | E3: =B3*C3*D3 -> 79664484 | F3: =0.0782 -> 0.0782 | G3: =F3*E3 -> 6229762.7 | H3: 17.68 kW rated but 14.14 kW due to 80% loading; 264.978825m^3 (70000 gal), Scale of 5 out of 10; density of 1000 kg/m^3; scaled up for 80% motor power loading; all else left at default; assuming 2 d of growth, 2d of biolixiviant production, 0.1 d of pH adjustment, 0.1 d of magnesite formation; https://checalc.com/solved/agitator.html
A4: Electricity - heating | E4: =(Inputs!B3*A25*A20)*(A21-A22)/(A23*A24) -> 7.0103593e+08 | F4: =F3 -> 0.0782 | G4: =F4*E4 -> 54821010
A5: Electricity - air pump | B5: 57.5 | C5: ='Capital Costs'!G5+'Capital Costs'!G14 -> 3627.942 | D5: =D3 -> 7200 | E5: =B5*C5*D5 -> 1.501968e+09 | F5: =F3 -> 0.0782 | G5: =F5*E5 -> 1.174539e+08 | H5: 57.50 hp, which converts to 42.29118 kW; 70,000 cfm, all else left at default; https://checalc.com/fan.html
A6: Electricity - liquid pump | B6: 31.155727 | C6: ='Capital Costs'!G8*5 -> 39.520065 | D6: =D3 -> 7200 | E6: =B6*C6*D6 -> 8865189.8 | F6: =F5 -> 0.0782 | G6: =F6*E6 -> 693257.84 | H6: 350 gpm, all else left at default; 42.36 bhp, which converts to 31.5878466 kW, 200 min ea for 6x transfers (among different tank types); https://checalc.com/calc/pump.html
A7: Electricity - total | E7: =SUM(E3:E6) -> 2.2915336e+09 | G7: =SUM(G3:G6) -> 1.7919793e+08 | H7: national industrial average March 2024 (https://www.eia.gov/electricity/monthly/epm_table_grapher.php?t=epmt_5_6_a)
A9: Wastewater Treatment | B9: $6.95 / kGal | G9: =6.95*Inputs!B3/(1000*3.78541) -> 8305853.1 | H9: average industrial wastewater treatment cost https://www.osti.gov/servlets/purl/1975260
A10: Labor | B10: Units | C10: Operators per Unit per Shift | D10: Operators per Shift | E10: Hours/y | F10: $/Hour | G10: $/y
A11: Reactors & Clarifiers (operating) | B11: =2*('Capital Costs'!G2)+'Capital Costs'!G7+'Capital Costs'!G11 -> 996.90564 | C11: 0.5 | D11: =B11*C11 -> 498.45282 | E11: =D11*24*'Capital Costs'!B19 -> 3588860.3 | F11: 27.78 | G11: =E11*F11 -> 99698540 | H11: $27.78 per https://www.bls.gov/ooh/life-physical-and-social-science/chemical-technicians.htm; use 0.5 for reactors and 0.2 for clarifiers per pg 312 of Biorenewable Resources
A12: Supervisory | G12: =0.15*G11 -> 14954781 | H12: 10-20% (using 15%) of operating labor costs per Biorenewable Resources (pg 311)
A13: Maintenance & repairs | G13: =0.06*'FCI, Taxes, Insurance'!C21 -> 1.6981648e+08 | H13: 2-10% (using 6%) of FCI costs per Biorenewable Resources (pg 312)
A14: Operating Supplies | G14: =0.15*G13 -> 25472472 | H14: 10-20% (using 15%) of maintenance & repair costs per Biorenewable Resources (pg 312)
A15: Laboratory expenses | G15: =0.15*G11 -> 14954781 | H15: 10-20% (using 15%) of operating labor costs per Biorenewable Resources (pg 312)
A16: Overhead (includes administrative) | G16: =0.6*(G11+G12) -> 68791992 | H16: 50-70% (using 60%) of operating labor costs per Biorenewable Resources (pg 313); Overhead includes fringe benefits, social security taxes, unemployment insurance, and retirement funds for workers at a facility. It can be a significant fraction of total labor costs and is usually estimated as 50–70% of costs for labor, supervision, and maintenance and repair (which is mostly labor). Overhead (of which administrative costs are a subset per https://www.investopedia.com/terms/o/overhead.asp)
F17: Total: | G17: =G7+G9+SUM(G11:G16) -> 5.8119282e+08
A20: 4.184 | B20: J/g C
A21: 100 | B21: Temp, final (C)
A22: 20 | B22: Temp, initial (C)
A23: 3600000 | B23: J/kWh
A24: 0.6 | B24: Heating efficiency
A25: 1000 | B25: g / L

Sheet Direct Cost Breakdown 
A1: Inputs | B1: Yeast extract | C1: =Inputs!I5 -> 3.524867e+08
B2: Water | C2: =Inputs!I3 -> 4613034.9
B3: Glucose | C3: =Inputs!I4 -> 1.2067486e+09
B4: NaOH | C4: =Inputs!I6 -> 70174.635
A5: Capital | B5: Tanks, agitators, diffusers, pumps, heap leaching pad | C5: ='Capital Costs'!L16 -> 9.2453358e+08
A6: Operating | B6: Electricity | C6: ='Operating Costs'!G7 -> 1.7919793e+08
B7: Wastewater treatment | C7: ='Operating Costs'!G9 -> 8305853.1
B8: Labor | C8: ='Operating Costs'!G11+'Operating Costs'!G12 -> 1.1465332e+08
B9: Maintenance & repairs | C9: ='Operating Costs'!G13 -> 1.6981648e+08
B10: Operating supplies | C10: ='Operating Costs'!G14 -> 25472472
B11: Laboratory expenses | C11: ='Operating Costs'!G15 -> 14954781
F12: Material | G12: =C1+C3+C4 -> 1.5593054e+09
F13: Water | G13: =C2 -> 4613034.9
F14: Electricity | G14: =C6 -> 1.7919793e+08
F15: Labor | G15: =C8 -> 1.1465332e+08
F16: Equipment | G16: =C5 -> 9.2453358e+08
F17: Other | G17: =C7+C9+C10+C11 -> 2.1854958e+08

Sheet FCI, Taxes, Insurance
C2: Total | D2: Annualized (20 year)
A3: State Tax | B3: 0.07 | D3: =-1*B3*Overall!B11 -> -7751464.3 | E3: Max Tax / t CO2 captured & stored
A4: Corporate Tax | B4: 0.21 | D4: =-1*B4*Overall!B11 -> -23254393 | E4: Max Tax / t CO2 captured & stored
A5: Property Tax | B5: 2% of FCI | D5: =0.02*C21 -> 56605493 | F5: =D5/$D$17 -> 0.31010869
A6: Piping | B6: 31% of PEC | C6: =0.31*B19 -> 2.8660541e+08 | D6: =C6/20 -> 14330270 | F6: =D6/$D$17 -> 0.078507248
A7: Instrumentation and control | B7: 18% of PEC | C7: =0.18*B19 -> 1.6641604e+08 | D7: =C7/20 -> 8320802.2 | F7: =D7/$D$17 -> 0.045584854
A8: Electrical equipment and materials | B8: 10% of PEC | C8: =0.1*B19 -> 92453358 | D8: =C8/20 -> 4622667.9 | F8: =D8/$D$17 -> 0.025324919
A9: Buildings | B9: 38% of PEC | C9: =0.38*B19 -> 3.5132276e+08 | D9: =C9/20 -> 17566138 | F9: =D9/$D$17 -> 0.096234691
A10: Service facilities | B10: 40% of PEC | C10: =0.4*B19 -> 3.6981343e+08 | D10: =C10/20 -> 18490672 | F10: =D10/$D$17 -> 0.10129967
A11: Yard improvement | B11: 10% of PEC | C11: =0.1*B19 -> 92453358 | D11: =C11/20 -> 4622667.9 | F11: =D11/$D$17 -> 0.025324919
A12: Land | B12: 6% of PEC | C12: =0.06*B19 -> 55472015 | D12: =C12/20 -> 2773600.7 | F12: =D12/$D$17 -> 0.015194951
A13: Engineering and supervision | B13: 8% of TDC | C13: =0.08*B20 -> 1.871256e+08 | D13: =C13/20 -> 9356279.8 | F13: =D13/$D$17 -> 0.051257635
A14: Construction expenses | B14: 10% of TDC | C14: =0.1*B20 -> 2.33907e+08 | D14: =C14/20 -> 11695350 | F14: =D14/$D$17 -> 0.064072044
A15: Contractors fee | B15: 5% of TDC | C15: =0.05*B20 -> 1.169535e+08 | D15: =C15/20 -> 5847674.9 | F15: =D15/$D$17 -> 0.032036022
A16: Insurance | B16: 1% of FCI | D16: =0.01*C21 -> 28302746 | F16: =D16/$D$17 -> 0.15505435
C17: Total | D17: =SUM(D5:D16) -> 1.8253436e+08 | F17: =D17/$D$17 -> 1
A19: PEC | B19: ='Capital Costs'!L16 -> 9.2453358e+08 | C19: =B19/20 -> 46226679
A20: TDC | B20: =B19+SUM(C6:C12) -> 2.33907e+09 | C20: =B20/20 -> 1.169535e+08
A21: FCI | C21: =1.21*B20 -> 2.8302746e+09

Sheet Outputs
B1: tonne leached metal / tonne leached rock | C1: tonne leached metal / y | D1: Selling price (unconverted) | E1: Selling Price | F1: Units | G1: 100% Revenue | H1: Discounted Revenue | I1: Units | K1: Price Source
A2: Si | B2: 0.20906198 | C2: =$G$19*$G$20*B2 -> 510718.03 | D2: $55.67 / tonne (SiO2) | E2: 55.67 | F2: $ / tonne | G2: =C2*E2*(60.08/28.0855) -> 60820526 | H2: =G2*$G$22 -> 40342105 | I2: $ / y | K2: https://www.chemanalyst.com/Pricing-data/silica-1304
A3: Ti | B3: 0.00023286864 | C3: =$G$19*$G$20*B3 -> 568.87537 | D3: 6712.69 EUR / tonne | E3: 6182 | F3: $ / tonne | G3: =C3*E3 -> 3516787.6 | H3: =G3*$G$22 -> 2332676.5 | I3: $ / y | K3: https://tradingeconomics.com/commodity/titanium
A4: Al | B4: 0.0067792197 | C4: =$G$19*$G$20*B4 -> 16560.972 | D4: 2590.69 EUR / tonne | E4: 2386 | F4: $ / tonne | G4: =C4*E4 -> 39514480 | H4: =G4*$G$22 -> 26209857 | I4: $ / y | K4: https://www.kitco.com/price/base-metals
A5: Cr | B5: 0.00069266791 | C5: =$G$19*$G$20*B5 -> 1692.1201 | E5: 9343 | F5: $ / tonne | G5: =C5*E5 -> 15809478 | H5: =G5*$G$22 -> 10486388 | I5: $ / y | K5: https://price.metal.com/Chromium
A6: Fe | B6: 0.062697571 | C6: =$G$19*$G$20*B6 -> 153164.05 | E6: 92 | F6: $ / tonne | G6: =C6*E6 -> 14091093 | H6: =G6*$G$22 -> 9346586.9 | I6: $ / y | K6: https://markets.businessinsider.com/commodities/iron-ore-price
A7: Mn | B7: 0.0010309865 | C7: =$G$19*$G$20*B7 -> 2518.5994 | E7: 413.2 | F7: $ / tonne | G7: =C7*E7 -> 1040685.3 | H7: =G7*$G$22 -> 690283.98 | I7: $ / y | K7: https://tradingeconomics.com/commodity/manganese
A8: Mg | B8: 0.26542909 | C8: =$G$19*$G$20*B8 -> 648417.37 | F8: $ / tonne | G8: 0 | I8: $ / y | J8: sell none - sequester all geologically
A9: Credit | B9: =G21*C9 -> 1056678.9 | C9: =C8*44.009/24.305 -> 1174087.6 | D9: $180 / tonne for 12 years of plant's 2 yr life | E9: =180*12/20 -> 108 | F9: $ / tonne | G9: =B9*E9 -> 1.1412132e+08 | H9: =G9 -> 1.1412132e+08 | I9: $ / y | J9: DAC + geologically sequestered; not discounted | K9: https://crsreports.congress.gov/product/pdf/IF/IF11455
A10: Ca | B10: 0.0089248903 | C10: =$G$19*$G$20*B10 -> 21802.636 | D10: 6182.43 EUR / tonne | E10: =$B$17*6182.43 -> 6713.5007 | F10: $ / tonne | G10: =C10*E10 -> 1.4637202e+08 | H10: =G10*$G$22 -> 97088198 | I10: $ / y | K10: Calcium Granule Electrolytic 98.5%min EXW China 6182,43 EUR mt https://ise-metal-quotes.com/
A11: Na | B11: 0.0006657694 | C11: =$G$19*$G$20*B11 -> 1626.4097 | D11: $2250 / tonne | E11: 2250 | F11: $ / tonne | G11: =C11*E11 -> 3659421.8 | H11: =G11*$G$22 -> 2427285.5 | I11: $ / y | K11: https://www.made-in-china.com/products-search/hot-china-products/Wholesale_Pure_Sodium_Metal.html
A12: K | B12: 0.00052701021 | C12: =$G$19*$G$20*B12 -> 1287.4345 | D12: $850 / kg | E12: =850*1000 -> 850000 | F12: $ / tonne | G12: =C12*E12 -> 1.0943194e+09 | H12: =G12*$G$22 -> 7.2585933e+08 | I12: $ / y | K12: https://material-properties.org/Potassium-properties-applications-price-production/#:~:text=They%20are%20primarily%20driven%20by%20supply%2C%20demand%20and,of%20pure%20Potassium%20were%20at%20around%20850%20%24%2Fkg.
A13: P | B13: 0.00012174389 | C13: =$G$19*$G$20*B13 -> 297.40845 | D13: $300 / tonne | E13: 300 | F13: $ / tonne | G13: =C13*E13 -> 89222.536 | H13: =G13*$G$22 -> 59181.088 | I13: $ / y | K13: http://www.leonland.de/elements_by_price/en/list
A14: Ni | B14: 0.0021835567 | C14: =$G$19*$G$20*B14 -> 5334.2161 | E14: 15830 | F14: $ / tonne | G14: =C14*E14 -> 84440641 | H14: =G14*$G$22 -> 56009269 | I14: $ / y | K14: https://www.kitco.com/price/base-metals
A15: Co | B15: 0.00011210502 | C15: =$G$19*$G$20*B15 -> 273.86164 | E15: 24300 | F15: $ / tonne | G15: =C15*E15 -> 6654837.8 | H15: =G15*$G$22 -> 4414137.5 | I15: $ / y | K15: https://tradingeconomics.com/commodity/cobalt
C16: =SUM(C2:C7)+SUM(C10:C15) -> 715844.61 | G16: =SUM(G2:G15) -> 1.5844499e+09 | H16: =SUM(H2:H15) -> 1.0893866e+09 | K16: Magnesite Lump 47%min EXW China 64,33 EUR mt https://ise-metal-quotes.com/
A17: USD/EUR: | B17: 1.0859 | C17: https://themoneyconverter.com/EUR/USD
C19: =C2*(60.08/28.0855) -> 1092518.9 | F19: Tailings (t/y) | G19: 2714336.1
F20: Leaching efficiency low | G20: 0.9
F21: CO2 Mineralization Efficiency | G21: 0.9
F22: Discount for metals removal & purification (Ni production costs/NI market value) | G22: =G26 -> 0.66329754
F23: Ni leaching costs ($/t) | G23: =(50000/20+8000) -> 10500 | H23: https://doi.org/10.3390/su151310496
F24: Ni production costs (assume market value $/t) | G24: =E14 -> 15830
F26: Fraction of Ni production costs we replace (leaching; what we can sell Ni for) | G26: =G23/G24 -> 0.66329754

Sheet Overall
B1: Cost Lo ($/y) | C1: Cost Lo ($/tCO2) | D1: Cost Hi ($/y) | E1: Cost Hi ($/tCO2)
A2: Inputs | B2: =Inputs!G7 -> 2.7604664e+08 | C2: =B2/Outputs!$B$9 -> 261.23986 | D2: =Inputs!H7 -> 2.85165e+09 | E2: =D2/Outputs!$B$9 -> 2698.6912
A3: Operating | B3: =D3 -> 5.8119282e+08 | C3: =B3/Outputs!$B$9 -> 550.0184 | D3: ='Operating Costs'!G17 -> 5.8119282e+08 | E3: =D3/Outputs!$B$9 -> 550.0184
A4: Capital | B4: =D4 -> 46226679 | C4: =B4/Outputs!$B$9 -> 43.747141 | D4: ='Capital Costs'!M16 -> 46226679 | E4: =D4/Outputs!$B$9 -> 43.747141
A5: FCI, Taxes, Insurance | B5: =D5 -> 1.8253436e+08 | C5: =B5/Outputs!$B$9 -> 172.74346 | D5: ='FCI, Taxes, Insurance'!D17 -> 1.8253436e+08 | E5: =D5/Outputs!$B$9 -> 172.74346
A6: Cost (No Credits) | B6: =SUM(B2:B5) -> 1.0860005e+09 | C6: =B6/Outputs!$B$9 -> 1027.7489 | D6: =SUM(D2:D5) -> 3.6616038e+09 | E6: =D6/Outputs!$B$9 -> 3465.2002
A7: Credits | B7: =D7 -> -1.1412132e+08 | C7: =B7/Outputs!$B$9 -> -108 | D7: =-1*Outputs!H9 -> -1.1412132e+08 | E7: =D7/Outputs!$B$9 -> -108
A8: Cost (With Credits) | B8: =B6+B7 -> 9.7187919e+08 | C8: =B8/Outputs!$B$9 -> 919.74886 | D8: =D6+D7 -> 3.5474825e+09 | E8: =D8/Outputs!$B$9 -> 3357.2002
A9: Metals Sales | B9: =D9 -> -9.752653e+08 | C9: =B9/Outputs!$B$9 -> -922.95335 | D9: =-1*(Outputs!H16-Outputs!H9) -> -9.752653e+08 | E9: =D9/Outputs!$B$9 -> -922.95335
A10: Cost (With Credits & Metals Sales) | B10: =B8+B9 -> -3386112.9 | C10: =B10/Outputs!$B$9 -> -3.2044863 | D10: =SUM(D2:D5)+D7+D9 -> 2.5722172e+09 | E10: =D10/Outputs!$B$9 -> 2434.2469
A11: Cost (With Metals Sales & No Credits Prior to Taxes) | B11: =SUM(B6)+B9 -> 1.107352e+08 | C11: =B11/Outputs!$B$9 -> 104.79551 | D11: =SUM(D2:D5)+D9 -> 2.6863385e+09 | E11: =D11/Outputs!$B$9 -> 2542.2469
A12: Taxes (28% of Profits) | C12: =B12/Outputs!$B$9 -> 0 | E12: =D12/Outputs!$B$9 -> 0
A13: Cost (With Credits & Metals Sales - After Taxes) | B13: =B11+B12+B7 -> -3386112.9 | C13: =B13/Outputs!$B$9 -> -3.2044863 | D13: =D11-D12+D7 -> 2.5722172e+09 | E13: =D13/Outputs!$B$9 -> 2434.2469
A14: Cost (With Metals Sales & No Credits after Taxes) | B14: =B11-B12 -> 1.107352e+08 | C14: =B14/Outputs!$B$9 -> 104.79551 | D14: =D11-D12 -> 2.6863385e+09 | E14: =D14/Outputs!$B$9 -> 2542.2469

Sheet CO2 Requirement
C2: Source
A3: 430 | B3: ppm CO2 (by volume) | C3: https://science.nasa.gov/earth/explore/earth-indicators/carbon-dioxide/
A4: 28.97 | B4: g air / mol air | C4: https://www.hamiltoncompany.com/knowledge-base/article/composition-of-the-atmosphere
A5: 44.009 | B5: g CO2 / mol CO2
A6: 1.225 | B6: kg air / m3 air | C6: https://www.jetir.org/papers/JETIR2407154.pdf
A7: =(A3/1000000)*A5/A4 -> 0.00065322299 | B7: kg CO2 / kg air
A8: =A7*(A6/1000) -> 8.0019816e-07 | B8: kg CO2 / L air
A9: 70000 | B9: cfm
A10: 4 | B10: pumps per tank
A11: =A10*A9 -> 280000 | B11: total cfm
A12: 28.3168 | B12: L / ft3
A13: =A12*A11 -> 7928704 | B13: L air / min
A14: =A13*60*24*10 -> 114173337600 | B14: L air / 10 days
A15: =A8*A14 -> 91361.295 | B15: kg CO2 / 10 days
A16: 70000 | B16: gal / tank
A17: =A16*3.785 -> 264950 | B17: L / tank
A18: =600/1000 -> 0.6 | B18: kg rock / L leachate
A19: 0.26542909 | B19: kg Mg / kg rock
A20: =A19*A18 -> 0.15925745 | B20: kg Mg / L leachate
A21: =A20*Outputs!G20 -> 0.14333171 | B21: kg Mg / L leachate (decreased for leaching efficiency)
A22: =A21*A17 -> 37975.736 | B22: kg Mg / tank
A23: =A5/24.305 -> 1.8106974 | B23: kg CO2 required / kg Mg
A24: =A22*A23 -> 68762.566 | B24: kg CO2 required / tank
A25: =A15/A24 -> 1.3286487 | B25: Supplied CO2 / required CO2

Sheet Comparison
A1: Method | B1: Function | C1: Cost Estimate (Lo, $/t CO2) | D1: Cost Estimate (Median, $/t CO2) | E1: Cost Estimate (Hi, $/t CO2) | F1: Sequestration Potential Range (Lo, Gt CO2/y) | G1: Sequestration Potential Range (Median, Gt CO2/y) | H1: Sequestration Potential Range (Hi, Gt CO2/y) | I1: Technology Readiness Level
A2: Biochar | B2: Capture + store | C2: -150 | D2: 40 | E2: 670 | F2: 0.03 | G2: 0.2 | H2: 1 | I2: 7
A3: Accelerated Weathering | B3: Capture + store | C3: 20 | D3: 70 | E3: 540 | F3: 0.001 | G3: 3.7 | H3: 18 | I3: 3
A4: Bio-accelerated Weathering | B4: Capture + store | C4: 3 | D4: =(C4+E4)/2 -> 1734 | E4: 3465 | F4: 0.001 | G4: =G3 -> 3.7 | H4: 18 | I4: 3
A5: Afforestation and Reforestation | B5: Capture + temporarily store | C5: 2 | D5: 30 | E5: 100 | F5: 0.01 | G5: 1.1 | H5: 14 | I5: 8
A6: Soil Carbon Sequestration | B6: Capture + temporarily store | C6: 5.5 | D6: 8 | E6: 11 | F6: 0.1 | G6: 1.3 | H6: 13 | I6: 7
A7: Ocean Fertilization | B7: Capture + temporarily store | C7: 10 | D7: 30 | E7: 290 | F7: 1 | G7: 4 | H7: 11 | I7: 7
A8: Enhanced Oil Recovery (EOR)* | B8: Store | C8: 17 | D8: 40 | E8: 50 | F8: 0.05 | G8: 65 | H8: 370 | I8: 8
A9: Direct Air Capture (DAC) | B9: Capture | C9: 30 | D9: 345 | E9: 1050 | F9: 0.0004 | G9: 1 | H9: 16 | I9: 7
